cdktf_metaflow_aws/__init__.py
cdktf_metaflow_aws/py.typed
cdktf_metaflow_aws/_jsii/__init__.py
cdktf_metaflow_aws/_jsii/cdktf-metaflow-aws@0.0.0.jsii.tgz
cdktf_metaflow_aws-0.0.0.dist-info/LICENSE
cdktf_metaflow_aws-0.0.0.dist-info/METADATA
cdktf_metaflow_aws-0.0.0.dist-info/WHEEL
cdktf_metaflow_aws-0.0.0.dist-info/top_level.txt
cdktf_metaflow_aws-0.0.0.dist-info/RECORD
