Metadata-Version: 2.1
Name: cdktf-metaflow-aws
Version: 0.0.0
Summary: cdktf-metaflow-aws
Home-page: https://github.com/bcgalvin/cdktf-metaflow-aws.git
Author: Bryan Galvin<bcgalvin@gmail.com>
License: Apache-2.0
Project-URL: Source, https://github.com/bcgalvin/cdktf-metaflow-aws.git
Classifier: Intended Audience :: Developers
Classifier: Operating System :: OS Independent
Classifier: Programming Language :: JavaScript
Classifier: Programming Language :: Python :: 3 :: Only
Classifier: Programming Language :: Python :: 3.7
Classifier: Programming Language :: Python :: 3.8
Classifier: Programming Language :: Python :: 3.9
Classifier: Programming Language :: Python :: 3.10
Classifier: Programming Language :: Python :: 3.11
Classifier: Typing :: Typed
Classifier: Development Status :: 5 - Production/Stable
Classifier: License :: OSI Approved
Requires-Python: ~=3.7
License-File: LICENSE
Requires-Dist: cdktf (>=0.17.0)
Requires-Dist: constructs (>=10.0.107)
Requires-Dist: jsii (<2.0.0,>=1.84.0)
Requires-Dist: publication (>=0.0.3)
Requires-Dist: typeguard (~=2.13.3)
